zk2jy360.py
Tests/__init__.py
Tests/tests.py
zk2jy360-1.0.0.dist-info/METADATA
zk2jy360-1.0.0.dist-info/WHEEL
zk2jy360-1.0.0.dist-info/top_level.txt
zk2jy360-1.0.0.dist-info/RECORD
