Metadata-Version: 2.1
Name: zk2jy360
Version: 1.0.0
Summary: This is the module of ZK attendance machine submitting attendance data to Jianyan360.
Home-page: http://www.jianyan360.com
Author: Zhouyun
Author-email: 251920948@qq.com
License: UNKNOWN
Keywords: ZK jianyan360
Platform: UNKNOWN
Classifier: Development Status :: 3 - Alpha
Classifier: Intended Audience :: Developers
Classifier: Topic :: Software Development :: Build Tools
Classifier: License :: OSI Approved :: MIT License
Classifier: Programming Language :: Python :: 2.7
Requires-Dist: requests
